tree_sitter_ziggy/__init__.pyi
tree_sitter_ziggy/binding.c
tree_sitter_ziggy/__init__.py
tree_sitter_ziggy/py.typed
tree_sitter_ziggy/_binding.abi3.so
tree_sitter_ziggy-0.1.0.dist-info/RECORD
tree_sitter_ziggy-0.1.0.dist-info/LICENSE
tree_sitter_ziggy-0.1.0.dist-info/WHEEL
tree_sitter_ziggy-0.1.0.dist-info/top_level.txt
tree_sitter_ziggy-0.1.0.dist-info/METADATA
